<?xml version="1.0"?>
<font>
<glyphs>
<!--
<glyph UID='0020'><base UID='0020' font="1"/></glyph>
<glyph UID='0021'><base UID='0021' font="1"/></glyph>
<glyph UID='0022'><base UID='0022' font="1"/></glyph>
<glyph UID='0023'><base UID='0023' font="1"/></glyph>
<glyph UID='0024'><base UID='0024' font="1"/></glyph>
<glyph UID='0025'><base UID='0025' font="1"/></glyph>
<glyph UID='0026'><base UID='0026' font="1"/></glyph>
<glyph UID='0027'><base UID='0027' font="1"/></glyph>
<glyph UID='0028'><base UID='0028' font="1"/></glyph>
<glyph UID='0029'><base UID='0029' font="1"/></glyph>
<glyph UID='002A'><base UID='002A' font="1"/></glyph>
<glyph UID='002B'><base UID='002B' font="1"/></glyph>
<glyph UID='002C'><base UID='002C' font="1"/></glyph>
<glyph UID='002D'><base UID='002D' font="1"/></glyph>
<glyph UID='002E'><base UID='002E' font="1"/></glyph>
<glyph UID='002F'><base UID='002F' font="1"/></glyph>
<glyph UID='0030'><base UID='0030' font="1"/></glyph>
<glyph UID='0031'><base UID='0031' font="1"/></glyph>
<glyph UID='0032'><base UID='0032' font="1"/></glyph>
<glyph UID='0033'><base UID='0033' font="1"/></glyph>
<glyph UID='0034'><base UID='0034' font="1"/></glyph>
<glyph UID='0035'><base UID='0035' font="1"/></glyph>
<glyph UID='0036'><base UID='0036' font="1"/></glyph>
<glyph UID='0037'><base UID='0037' font="1"/></glyph>
<glyph UID='0038'><base UID='0038' font="1"/></glyph>
<glyph UID='0039'><base UID='0039' font="1"/></glyph>
<glyph UID='003A'><base UID='003A' font="1"/></glyph>
<glyph UID='003B'><base UID='003B' font="1"/></glyph>
<glyph UID='003C'><base UID='003C' font="1"/></glyph>
<glyph UID='003D'><base UID='003D' font="1"/></glyph>
<glyph UID='003E'><base UID='003E' font="1"/></glyph>
<glyph UID='003F'><base UID='003F' font="1"/></glyph>
<glyph UID='0040'><base UID='0040' font="1"/></glyph>
<glyph UID='0041'><base UID='0041' font="1"/></glyph>
<glyph UID='0042'><base UID='0042' font="1"/></glyph>
<glyph UID='0043'><base UID='0043' font="1"/></glyph>
<glyph UID='0044'><base UID='0044' font="1"/></glyph>
<glyph UID='0045'><base UID='0045' font="1"/></glyph>
<glyph UID='0046'><base UID='0046' font="1"/></glyph>
<glyph UID='0047'><base UID='0047' font="1"/></glyph>
<glyph UID='0048'><base UID='0048' font="1"/></glyph>
<glyph UID='0049'><base UID='0049' font="1"/></glyph>
<glyph UID='004A'><base UID='004A' font="1"/></glyph>
<glyph UID='004B'><base UID='004B' font="1"/></glyph>
<glyph UID='004C'><base UID='004C' font="1"/></glyph>
<glyph UID='004D'><base UID='004D' font="1"/></glyph>
<glyph UID='004E'><base UID='004E' font="1"/></glyph>
<glyph UID='004F'><base UID='004F' font="1"/></glyph>
<glyph UID='0050'><base UID='0050' font="1"/></glyph>
<glyph UID='0051'><base UID='0051' font="1"/></glyph>
<glyph UID='0052'><base UID='0052' font="1"/></glyph>
<glyph UID='0053'><base UID='0053' font="1"/></glyph>
<glyph UID='0054'><base UID='0054' font="1"/></glyph>
<glyph UID='0055'><base UID='0055' font="1"/></glyph>
<glyph UID='0056'><base UID='0056' font="1"/></glyph>
<glyph UID='0057'><base UID='0057' font="1"/></glyph>
<glyph UID='0058'><base UID='0058' font="1"/></glyph>
<glyph UID='0059'><base UID='0059' font="1"/></glyph>
<glyph UID='005A'><base UID='005A' font="1"/></glyph>
<glyph UID='005B'><base UID='005B' font="1"/></glyph>
<glyph UID='005C'><base UID='005C' font="1"/></glyph>
<glyph UID='005D'><base UID='005D' font="1"/></glyph>
<glyph UID='005E'><base UID='005E' font="1"/></glyph>
<glyph UID='005F'><base UID='005F' font="1"/></glyph>
<glyph UID='0060'><base UID='0060' font="1"/></glyph>
<glyph UID='0061'><base UID='0061' font="1"/></glyph>
<glyph UID='0062'><base UID='0062' font="1"/></glyph>
<glyph UID='0063'><base UID='0063' font="1"/></glyph>
<glyph UID='0064'><base UID='0064' font="1"/></glyph>
<glyph UID='0065'><base UID='0065' font="1"/></glyph>
<glyph UID='0066'><base UID='0066' font="1"/></glyph>
<glyph UID='0067'><base UID='0067' font="1"/></glyph>
<glyph UID='0068'><base UID='0068' font="1"/></glyph>
<glyph UID='0069'><base UID='0069' font="1"/></glyph>
<glyph UID='006A'><base UID='006A' font="1"/></glyph>
<glyph UID='006B'><base UID='006B' font="1"/></glyph>
<glyph UID='006C'><base UID='006C' font="1"/></glyph>
<glyph UID='006D'><base UID='006D' font="1"/></glyph>
<glyph UID='006E'><base UID='006E' font="1"/></glyph>
<glyph UID='006F'><base UID='006F' font="1"/></glyph>
<glyph UID='0070'><base UID='0070' font="1"/></glyph>
<glyph UID='0071'><base UID='0071' font="1"/></glyph>
<glyph UID='0072'><base UID='0072' font="1"/></glyph>
<glyph UID='0073'><base UID='0073' font="1"/></glyph>
<glyph UID='0074'><base UID='0074' font="1"/></glyph>
<glyph UID='0075'><base UID='0075' font="1"/></glyph>
<glyph UID='0076'><base UID='0076' font="1"/></glyph>
<glyph UID='0077'><base UID='0077' font="1"/></glyph>
<glyph UID='0078'><base UID='0078' font="1"/></glyph>
<glyph UID='0079'><base UID='0079' font="1"/></glyph>
<glyph UID='007A'><base UID='007A' font="1"/></glyph>
<glyph UID='007B'><base UID='007B' font="1"/></glyph>
<glyph UID='007C'><base UID='007C' font="1"/></glyph>
<glyph UID='007D'><base UID='007D' font="1"/></glyph>
<glyph UID='007E'><base UID='007E' font="1"/></glyph>

<glyph UID="2018"><base UID="2018" font="1"/></glyph>
<glyph UID="2019"><base UID="2019" font="1"/></glyph>
<glyph UID="201C"><base UID="201C" font="1"/></glyph>
<glyph UID="201D"><base UID="201D" font="1"/></glyph>
-->

<!-- characters from legacy font files that were not mapped before -->
<glyph PSName="space.knda"><base UID="F020"><scale x="1.4" y="1.4"/></base></glyph>
<glyph PSName="exclam.knda"><base UID="F021"><scale x="1.4" y="1.4"/></base></glyph>
<glyph PSName="quoteleft.knda"><base UID="F022"><scale x="1.4" y="1.4"/></base></glyph>
<glyph PSName="quotedblleft.knda"><base UID="F022"><scale x="1.4" y="1.4"/></base><base UID="F022"><scale x="1.4" y="1.4"/></base></glyph>
<glyph UID="25CC" PSName="dottedcircle"><base UID="F023"><scale x="1.4" y="1.4"/></base></glyph>
<glyph PSName='spacingcandrabindu' UID='0C80'><base UID='F024'><scale x="1.4" y="1.4"/></base></glyph>
<glyph PSName='candrabindu' UID='0C81'><base UID='F024'><scale x="1.4" y="1.4"/></base></glyph>
<glyph UID="0950" PSName="om"><base UID="F024"><scale x="1.4" y="1.4"/></base></glyph>
<glyph PSName="na_virama"><base UID="F026"><scale x="1.4" y="1.4"/></base></glyph>
<glyph PSName="quoteright.knda"><base UID="F027"><scale x="1.4" y="1.4"/></base></glyph>
<glyph PSName="quotedblright.knda"><base UID="F027"><scale x="1.4" y="1.4"/></base><base UID="F027"><scale x="1.4" y="1.4"/></base></glyph>
<glyph PSName="parenleft.knda"><base UID="F028"><scale x="1.4" y="1.4"/></base></glyph>
<glyph PSName="parenright.knda"><base UID="F029"><scale x="1.4" y="1.4"/></base></glyph>
<glyph UID="0964" PSName="danda"><base UID="F02B"><scale x="1.4" y="1.4"/></base></glyph>
<glyph UID="0965" PSName="doubledanda"><base UID="F02B"><scale x="1.4" y="1.4"/></base><base UID="F02B"><scale x="1.4" y="1.4"/></base></glyph>
<glyph PSName="comma.knda"><base UID="F02C"><scale x="1.4" y="1.4"/></base></glyph>
<glyph PSName="hyphen.knda"><base UID="F02D"><scale x="1.4" y="1.4"/></base></glyph>
<glyph PSName="period.knda"><base UID="F02E"><scale x="1.4" y="1.4"/></base></glyph>
<glyph PSName="slash.knda"><base UID="F02F"><scale x="1.4" y="1.4"/></base></glyph>
<glyph PSName="zero.knda"><base UID="F030"><scale x="1.4" y="1.4"/></base></glyph>
<glyph PSName="one.knda"><base UID="F031"><scale x="1.4" y="1.4"/></base></glyph>
<glyph PSName="two.knda"><base UID="F032"><scale x="1.4" y="1.4"/></base></glyph>
<glyph PSName="three.knda"><base UID="F033"><scale x="1.4" y="1.4"/></base></glyph>
<glyph PSName="four.knda"><base UID="F034"><scale x="1.4" y="1.4"/></base></glyph>
<glyph PSName="five.knda"><base UID="F035"><scale x="1.4" y="1.4"/></base></glyph>
<glyph PSName="six.knda"><base UID="F036"><scale x="1.4" y="1.4"/></base></glyph>
<glyph PSName="seven.knda"><base UID="F037"><scale x="1.4" y="1.4"/></base></glyph>
<glyph PSName="eight.knda"><base UID="F038"><scale x="1.4" y="1.4"/></base></glyph>
<glyph PSName="nine.knda"><base UID="F039"><scale x="1.4" y="1.4"/></base></glyph>
<glyph PSName="colon.knda"><base UID="F03A"><scale x="1.4" y="1.4"/></base></glyph>
<glyph PSName="semicolon.knda"><base UID="F03B"><scale x="1.4" y="1.4"/></base></glyph>
<glyph PSName="question.knda"><base UID="F03F"><scale x="1.4" y="1.4"/></base></glyph>
<glyph PSName="nbsp.knda"><base UID="F020"><advance width="1400"/></base></glyph>
<glyph PSName='lvocalicmatra' UID='0CE2'><base UID='F04A'><scale x="1.4" y="1.4"/></base></glyph>
<glyph PSName='llvocalicmatra' UID='0CE3'><base UID='F04B'><scale x="1.4" y="1.4"/></base></glyph>
<glyph PSName='lvocalicmatra.alt'><base UID='F04A'><scale x="1.4" y="1.4"/></base></glyph>
<glyph PSName='llvocalicmatra.alt'><base UID='F04B'><scale x="1.4" y="1.4"/></base></glyph>
<glyph PSName='xmatra'><base UID='F0DC'><scale x="1.4" y="1.4"/></base></glyph>
<glyph PSName='jihvamuliya' UID='0CF1'><base UID='0078' font="1"/><scale x="1.0" y="1.0"/></glyph>
<glyph PSName='upadhmaniya' UID='0CF2'><base UID='F04E'><scale x="1.9" y="1.9"/></base></glyph>
<glyph PSName='udatta' UID='0951'><base UID='F09A'><scale x="1.4" y="1.4"/></base></glyph>
<glyph PSName='anudatta' UID='0952'><base UID='F09B'><scale x="1.4" y="1.4"/></base></glyph>
<glyph PSName='gravedeva' UID='0953'><base UID='F09C'><scale x="1.4" y="1.4"/></base></glyph>
<glyph PSName='acutedeva' UID='0954'><base UID='F09D'><scale x="1.4" y="1.4"/></base></glyph>
<glyph PSName='doublesvarita' UID='1CDA'><base UID='F09F'><scale x="1.4" y="1.4"/></base></glyph>

<!-- original non-roman mapping -->
<glyph PSName='angleleft'><base UID='F0E1'><scale x="1.4" y="1.4"/></base></glyph>
<glyph PSName='consonant_part'><base UID='F0DA'><scale x="1.4" y="1.4"/></base></glyph>
<glyph PSName='consonant_part1'><base UID='F0E1'><scale x="1.4" y="1.4"/></base></glyph>
<glyph PSName='short_rr'><base UID='F025'><scale x="1.4" y="1.4"/></base></glyph>
<glyph PSName='u00A0' UID='00A0'><base UID='F020'><scale x="1.4" y="1.4"/></base></glyph>
<glyph PSName='u0C82' UID='0C82'><base UID='F04D'><scale x="1.4" y="1.4"/></base></glyph>
<glyph PSName='u0C83' UID='0C83'><base UID='F04E'><scale x="1.4" y="1.4"/></base></glyph>
<glyph PSName='u0C85' UID='0C85'><base UID='F040'><scale x="1.4" y="1.4"/></base></glyph>
<glyph PSName='u0C86' UID='0C86'><base UID='F041'><scale x="1.4" y="1.4"/></base></glyph>
<glyph PSName='u0C87' UID='0C87'><base UID='F042'><scale x="1.4" y="1.4"/></base></glyph>
<glyph PSName='u0C88' UID='0C88'><base UID='F043'><scale x="1.4" y="1.4"/></base></glyph>
<glyph PSName='u0C89' UID='0C89'><base UID='F044'><scale x="1.4" y="1.4"/></base></glyph>
<glyph PSName='u0C8A' UID='0C8A'><base UID='F045'><scale x="1.4" y="1.4"/></base></glyph>
<glyph PSName='u0C8B' UID='0C8B'><base UID='F046'><scale x="1.4" y="1.4"/></base><base UID='F0DF'><scale x="1.4" y="1.4"/></base></glyph>
<glyph PSName='u0C8B_base'><base UID='F046'><scale x="1.4" y="1.4"/></base></glyph>
<glyph PSName='u0C8C' UID='0C8C'><base UID='F08B'><scale x="1.4" y="1.4"/></base><base UID='F0DF'><scale x="1.4" y="1.4"/></base></glyph>
<glyph PSName='u0C8C_base'><base UID='F08B'><scale x="1.4" y="1.4"/></base></glyph>
<glyph PSName='u0C8E' UID='0C8E'><base UID='F047'><scale x="1.4" y="1.4"/></base></glyph>
<glyph PSName='u0C8F' UID='0C8F'><base UID='F048'><scale x="1.4" y="1.4"/></base></glyph>
<glyph PSName='u0C90' UID='0C90'><base UID='F049'><scale x="1.4" y="1.4"/></base></glyph>
<glyph PSName='ovowel' UID='0C92'><base UID='F04A'><scale x="1.4" y="1.4"/></base></glyph>
<glyph PSName='oovowel' UID='0C93'><base UID='F04B'><scale x="1.4" y="1.4"/></base></glyph>
<glyph PSName='u0C94' UID='0C94'><base UID='F04C'><scale x="1.4" y="1.4"/></base></glyph>
<glyph PSName='u0C95' UID='0C95'><base UID='F04F'><scale x="1.4" y="1.4"/></base><base UID='F0DA'><scale x="1.4" y="1.4"/></base></glyph>
<glyph PSName='u0C95.base'><base UID='F04F'><scale x="1.4" y="1.4"/></base></glyph>
<glyph PSName='u0C95.imathra'><base UID='F050'><scale x="1.4" y="1.4"/></base></glyph>
<glyph PSName='u0C95.sub'><base UID='F051'><scale x="1.4" y="1.4"/></base></glyph>
<glyph PSName='u0C95_u0CC3.sub'><base UID='F0ED'><scale x="1.4" y="1.4"/></base></glyph>
<glyph PSName='u0C96' UID='0C96'><base UID='F052'><scale x="1.4" y="1.4"/></base></glyph>
<glyph PSName='u0C96.base'><base UID='F053'><scale x="1.4" y="1.4"/></base></glyph>
<glyph PSName='u0C96.imathra'><base UID='F054'><scale x="1.4" y="1.4"/></base></glyph>
<glyph PSName='u0C96.sub'><base UID='F055'><scale x="1.4" y="1.4"/></base></glyph>
<glyph PSName='u0C97' UID='0C97'><base UID='F056'><scale x="1.4" y="1.4"/></base><base UID='F0DA'><scale x="1.4" y="1.4"/></base></glyph>
<glyph PSName='u0C97.base'><base UID='F056'><scale x="1.4" y="1.4"/></base></glyph>
<glyph PSName='u0C97.imathra'><base UID='F057'><scale x="1.4" y="1.4"/></base></glyph>
<glyph PSName='u0C97.sub'><base UID='F058'><scale x="1.4" y="1.4"/></base></glyph>
<glyph PSName='u0C98' UID='0C98'><base UID='F059'><scale x="1.4" y="1.4"/></base><base UID='F0DA'><scale x="1.4" y="1.4"/></base></glyph>
<glyph PSName='u0C98.base'><base UID='F059'><scale x="1.4" y="1.4"/></base></glyph>
<glyph PSName='u0C98.imathra'><base UID='F05A'><scale x="1.4" y="1.4"/></base></glyph>
<glyph PSName='u0C98.sub'><base UID='F05B'><scale x="1.4" y="1.4"/></base></glyph>
<glyph PSName='u0C99' UID='0C99'><base UID='F05C'><scale x="1.4" y="1.4"/></base></glyph>
<glyph PSName='u0C99.sub'><base UID='F05D'><scale x="1.4" y="1.4"/></base></glyph>
<glyph PSName='u0C9A' UID='0C9A'><base UID='F05E'><scale x="1.4" y="1.4"/></base><base UID='F0DA'><scale x="1.4" y="1.4"/></base></glyph>
<glyph PSName='u0C9A.base'><base UID='F05E'><scale x="1.4" y="1.4"/></base></glyph>
<glyph PSName='u0C9A.imathra'><base UID='F05F'><scale x="1.4" y="1.4"/></base></glyph>
<glyph PSName='u0C9A.sub'><base UID='F060'><scale x="1.4" y="1.4"/></base></glyph>
<glyph PSName='u0C9B' UID='0C9B'><base UID='F061'><scale x="1.4" y="1.4"/></base><base UID='F0DA'><scale x="1.4" y="1.4"/></base></glyph>
<glyph PSName='u0C9B.base'><base UID='F061'><scale x="1.4" y="1.4"/></base></glyph>
<glyph PSName='u0C9B.imathra'><base UID='F062'><scale x="1.4" y="1.4"/></base></glyph>
<glyph PSName='u0C9B.sub'><base UID='F063'><scale x="1.4" y="1.4"/></base></glyph>
<glyph PSName='u0C9C' UID='0C9C'><base UID='F064'><scale x="1.4" y="1.4"/></base></glyph>
<glyph PSName='u0C9C.base'><base UID='F065'><scale x="1.4" y="1.4"/></base></glyph>
<glyph PSName='u0C9C.imathra'><base UID='F066'><scale x="1.4" y="1.4"/></base></glyph>
<glyph PSName='u0C9C.sub'><base UID='F067'><scale x="1.4" y="1.4"/></base></glyph>
<glyph PSName='u0C9D' UID='0C9D'><base UID='F0C1'><scale x="1.4" y="1.4"/></base><base UID='F0DA'><scale x="1.4" y="1.4"/></base><base UID='F068'><scale x="1.4" y="1.4"/></base><base UID='F0DF'><scale x="1.4" y="1.4"/></base></glyph>
<glyph PSName='u0C9D.base'><base UID='F0C1'><scale x="1.4" y="1.4"/></base><base UID='F068'><scale x="1.4" y="1.4"/></base><base UID='F0DF'><scale x="1.4" y="1.4"/></base></glyph>
<glyph PSName='u0C9D_half.base'><base UID='F0C1'><scale x="1.4" y="1.4"/></base><base UID='F068'><scale x="1.4" y="1.4"/></base></glyph>
<glyph PSName='u0C9D.imathra'><base UID='F0C2'><scale x="1.4" y="1.4"/></base><base UID='F068'><scale x="1.4" y="1.4"/></base><base UID='F0DF'><scale x="1.4" y="1.4"/></base></glyph>
<glyph PSName='u0C9D.sub'><base UID='F069'><scale x="1.4" y="1.4"/></base></glyph>
<glyph PSName='u0C9D_base'><base UID='F068'><scale x="1.4" y="1.4"/></base></glyph>
<glyph PSName='u0C9D.base.mathra'><base UID='F0C1'><scale x="1.4" y="1.4"/></base><base UID='F0DA'><scale x="1.4" y="1.4"/></base><base UID='F068'><scale x="1.4" y="1.4"/></base><base UID='F0E1'><scale x="1.4" y="1.4"/></base></glyph>
<glyph PSName='u0C9E' UID='0C9E'><base UID='F06A'><scale x="1.4" y="1.4"/></base></glyph>
<glyph PSName='u0C9E.sub'><base UID='F06B'><scale x="1.4" y="1.4"/></base></glyph>
<glyph PSName='u0C9F' UID='0C9F'><base UID='F06C'><scale x="1.4" y="1.4"/></base></glyph>
<glyph PSName='u0C9F.base'><base UID='F06D'><scale x="1.4" y="1.4"/></base></glyph>
<glyph PSName='u0C9F.imathra'><base UID='F06E'><scale x="1.4" y="1.4"/></base></glyph>
<glyph PSName='u0C9F.sub'><base UID='F06F'><scale x="1.4" y="1.4"/></base></glyph>
<glyph PSName='u0CA0' UID='0CA0'><base UID='F070'><scale x="1.4" y="1.4"/></base><base UID='F0DA'><scale x="1.4" y="1.4"/></base></glyph>
<glyph PSName='u0CA0.base'><base UID='F070'><scale x="1.4" y="1.4"/></base></glyph>
<glyph PSName='u0CA0.imathra'><base UID='F071'><scale x="1.4" y="1.4"/></base></glyph>
<glyph PSName='u0CA0.sub'><base UID='F072'><scale x="1.4" y="1.4"/></base></glyph>
<glyph PSName='u0CA1' UID='0CA1'><base UID='F073'><scale x="1.4" y="1.4"/></base><base UID='F0DA'><scale x="1.4" y="1.4"/></base></glyph>
<glyph PSName='u0CA1.base'><base UID='F073'><scale x="1.4" y="1.4"/></base></glyph>
<glyph PSName='u0CA1.imathra'><base UID='F074'><scale x="1.4" y="1.4"/></base></glyph>
<glyph PSName='u0CA1.sub'><base UID='F075'><scale x="1.4" y="1.4"/></base></glyph>
<glyph PSName='u0CA2' UID='0CA2'><base UID='F076'><scale x="1.4" y="1.4"/></base><base UID='F0DA'><scale x="1.4" y="1.4"/></base></glyph>
<glyph PSName='u0CA2.base'><base UID='F076'><scale x="1.4" y="1.4"/></base></glyph>
<glyph PSName='u0CA2.imathra'><base UID='F077'><scale x="1.4" y="1.4"/></base></glyph>
<glyph PSName='u0CA2.sub'><base UID='F078'><scale x="1.4" y="1.4"/></base></glyph>
<glyph PSName='u0CA3' UID='0CA3'><base UID='F079'><scale x="1.4" y="1.4"/></base></glyph>
<glyph PSName='u0CA3.base'><base UID='F07A'><scale x="1.4" y="1.4"/></base></glyph>
<glyph PSName='u0CA3.imathra'><base UID='F07B'><scale x="1.4" y="1.4"/></base></glyph>
<glyph PSName='u0CA3.sub'><base UID='F07C'><scale x="1.4" y="1.4"/></base></glyph>
<glyph PSName='u0CA4' UID='0CA4'><base UID='F07D'><scale x="1.4" y="1.4"/></base><base UID='F0DA'><scale x="1.4" y="1.4"/></base></glyph>
<glyph PSName='u0CA4.base'><base UID='F07D'><scale x="1.4" y="1.4"/></base></glyph>
<glyph PSName='u0CA4.imathra'><base UID='F07E'><scale x="1.4" y="1.4"/></base></glyph>
<glyph PSName='u0CA4.sub'><base UID='F0A1'><scale x="1.4" y="1.4"/></base></glyph>
<glyph PSName='u0CA4_u0CAF.sub'><base UID='F098'><scale x="1.4" y="1.4"/></base></glyph>
<glyph PSName='u0CA4_u0CB5.sub'><base UID='F0EC'><scale x="1.4" y="1.4"/></base></glyph>
<glyph PSName='u0CA4_u0CC3.sub'><base UID='F0EA'><scale x="1.4" y="1.4"/></base></glyph>
<glyph PSName='u0CA4_u0CD6.sub'><base UID='F0EB'><scale x="1.4" y="1.4"/></base></glyph>
<glyph PSName='u0CA5' UID='0CA5'><base UID='F0A2'><scale x="1.4" y="1.4"/></base><base UID='F0DA'><scale x="1.4" y="1.4"/></base></glyph>
<glyph PSName='u0CA5.base'><base UID='F0A2'><scale x="1.4" y="1.4"/></base></glyph>
<glyph PSName='u0CA5.imathra'><base UID='F0A3'><scale x="1.4" y="1.4"/></base></glyph>
<glyph PSName='u0CA5.sub'><base UID='F0A4'><scale x="1.4" y="1.4"/></base></glyph>
<glyph PSName='u0CA6' UID='0CA6'><base UID='F0A5'><scale x="1.4" y="1.4"/></base><base UID='F0DA'><scale x="1.4" y="1.4"/></base></glyph>
<glyph PSName='u0CA6.base'><base UID='F0A5'><scale x="1.4" y="1.4"/></base></glyph>
<glyph PSName='u0CA6.imathra'><base UID='F0A6'><scale x="1.4" y="1.4"/></base></glyph>
<glyph PSName='u0CA6.sub'><base UID='F0A7'><scale x="1.4" y="1.4"/></base></glyph>
<glyph PSName='u0CA7' UID='0CA7'><base UID='F0A8'><scale x="1.4" y="1.4"/></base><base UID='F0DA'><scale x="1.4" y="1.4"/></base></glyph>
<glyph PSName='u0CA7.base'><base UID='F0A8'><scale x="1.4" y="1.4"/></base></glyph>
<glyph PSName='u0CA7.imathra'><base UID='F0A9'><scale x="1.4" y="1.4"/></base></glyph>
<glyph PSName='u0CA7.sub'><base UID='F0AA'><scale x="1.4" y="1.4"/></base></glyph>
<glyph PSName='u0CA8' UID='0CA8'><base UID='F0AB'><scale x="1.4" y="1.4"/></base><base UID='F0DA'><scale x="1.4" y="1.4"/></base></glyph>
<glyph PSName='u0CA8.base'><base UID='F0AB'><scale x="1.4" y="1.4"/></base></glyph>
<glyph PSName='u0CA8.imathra'><base UID='F0AC'><scale x="1.4" y="1.4"/></base></glyph>
<glyph PSName='u0CA8.sub'><base UID='F0AD'><scale x="1.4" y="1.4"/></base></glyph>
<glyph PSName='u0CAA' UID='0CAA'><base UID='F0AE'><scale x="1.4" y="1.4"/></base><base UID='F0DA'><scale x="1.4" y="1.4"/></base></glyph>
<glyph PSName='u0CAA.base'><base UID='F0AE'><scale x="1.4" y="1.4"/></base></glyph>
<glyph PSName='u0CAA.imathra'><base UID='F0AF'><scale x="1.4" y="1.4"/></base></glyph>
<glyph PSName='u0CAA.sub'><base UID='F0B0'><scale x="1.4" y="1.4"/></base></glyph>
<glyph PSName='u0CAB' UID='0CAB'><base UID='F0B1'><scale x="1.4" y="1.4"/></base><base UID='F0DA'><scale x="1.4" y="1.4"/></base></glyph>
<glyph PSName='u0CAB.base'><base UID='F0B1'><scale x="1.4" y="1.4"/></base></glyph>
<glyph PSName='u0CAB.imathra'><base UID='F0B2'><scale x="1.4" y="1.4"/></base></glyph>
<glyph PSName='u0CAB.sub'><base UID='F0B5'><scale x="1.4" y="1.4"/></base></glyph>
<glyph PSName='u0CAC' UID='0CAC'><base UID='F0B6'><scale x="1.4" y="1.4"/></base></glyph>
<glyph PSName='u0CAC.base'><base UID='F0B7'><scale x="1.4" y="1.4"/></base></glyph>
<glyph PSName='u0CAC.imathra'><base UID='F0B8'><scale x="1.4" y="1.4"/></base></glyph>
<glyph PSName='u0CAC.sub'><base UID='F0B9'><scale x="1.4" y="1.4"/></base></glyph>
<glyph PSName='u0CAD' UID='0CAD'><base UID='F0BA'><scale x="1.4" y="1.4"/></base><base UID='F0DA'><scale x="1.4" y="1.4"/></base></glyph>
<glyph PSName='u0CAD.base'><base UID='F0BA'><scale x="1.4" y="1.4"/></base></glyph>
<glyph PSName='u0CAD.imathra'><base UID='F0BB'><scale x="1.4" y="1.4"/></base></glyph>
<glyph PSName='u0CAD.sub'><base UID='F0BC'><scale x="1.4" y="1.4"/></base></glyph>
<glyph PSName='u0CAE' UID='0CAE'><base UID='F0C8'><scale x="1.4" y="1.4"/></base><base UID='F0DA'><scale x="1.4" y="1.4"/></base><base UID='F0DF'><scale x="1.4" y="1.4"/></base></glyph>
<glyph PSName='u0CAE.base'><base UID='F0C8'><scale x="1.4" y="1.4"/></base><base UID='F0DF'><scale x="1.4" y="1.4"/></base></glyph>
<glyph PSName='u0CAE.imathra'><base UID='F0C9'><scale x="1.4" y="1.4"/></base><base UID='F0DF'><scale x="1.4" y="1.4"/></base></glyph>
<glyph PSName='u0CAE.sub'><base UID='F0BD'><scale x="1.4" y="1.4"/></base></glyph>
<glyph PSName='u0CAE.base.mathra'><base UID='F0C8'><scale x="1.4" y="1.4"/></base><base UID='F0DA'><scale x="1.4" y="1.4"/></base><base UID='F0E1'><scale x="1.4" y="1.4"/></base></glyph>
<glyph PSName='u0CAE_base'><base UID='F0C8'><scale x="1.4" y="1.4"/></base></glyph>
<glyph PSName='u0CAF' UID='0CAF'><base UID='F0BE'><scale x="1.4" y="1.4"/></base><base UID='F0DA'><scale x="1.4" y="1.4"/></base><base UID='F0DF'><scale x="1.4" y="1.4"/></base></glyph>
<glyph PSName='u0CAF.base'><base UID='F0BE'><scale x="1.4" y="1.4"/></base><base UID='F0DF'><scale x="1.4" y="1.4"/></base></glyph>
<glyph PSName='u0CAF.imathra'><base UID='F0BF'><scale x="1.4" y="1.4"/></base><base UID='F0DF'><scale x="1.4" y="1.4"/></base></glyph>
<glyph PSName='u0CAF.sub'><base UID='F0C0'><scale x="1.4" y="1.4"/></base></glyph>
<glyph PSName='u0CAF_base'><base UID='F0BE'><scale x="1.4" y="1.4"/></base></glyph>
<glyph PSName='u0CAF_base_i'><base UID='F0BF'><scale x="1.4" y="1.4"/></base></glyph>
<glyph PSName='u0CAF.base.mathra'><base UID='F0BE'><scale x="1.4" y="1.4"/></base><base UID='F0DA'><scale x="1.4" y="1.4"/></base><base UID='F0E1'><scale x="1.4" y="1.4"/></base></glyph>
<glyph PSName='u0CB0' UID='0CB0'><base UID='F0C1'><scale x="1.4" y="1.4"/></base><base UID='F0DA'><scale x="1.4" y="1.4"/></base></glyph>
<glyph PSName='u0CB0.base'><base UID='F0C1'><scale x="1.4" y="1.4"/></base></glyph>
<glyph PSName='u0CB0.below'><base UID='F0EF'><scale x="1.4" y="1.4"/></base></glyph>
<glyph PSName='u0CB0.imathra'><base UID='F0C2'><scale x="1.4" y="1.4"/></base></glyph>
<glyph PSName='u0CB0.below.ra'><base UID='F0C3'><scale x="1.4" y="1.4"/></base></glyph>
<glyph PSName='u0CB0.below.angleright'><base UID='F0F1'><scale x="1.4" y="1.4"/></base></glyph>
<glyph PSName='u0CB0.below.large'><base UID='F0F0'><scale x="1.4" y="1.4"/></base></glyph>
<glyph PSName='u0CB0_u0CD6.sub'><base UID='F0EE'><scale x="1.4" y="1.4"/></base></glyph>
<glyph PSName='u0CB1' UID='0CB1'><base UID='F090'><scale x="1.4" y="1.4"/></base></glyph>
<glyph PSName='u0CB1.imathra'><base UID='F091'><scale x="1.4" y="1.4"/></base></glyph>
<glyph PSName='u0CB1.sub'><base UID='F092'><scale x="1.4" y="1.4"/></base></glyph>
<glyph PSName='u0CB2' UID='0CB2'><base UID='F0C4'><scale x="1.4" y="1.4"/></base></glyph>
<glyph PSName='u0CB2.base'><base UID='F0C5'><scale x="1.4" y="1.4"/></base></glyph>
<glyph PSName='u0CB2.imathra'><base UID='F0C6'><scale x="1.4" y="1.4"/></base></glyph>
<glyph PSName='u0CB2.sub'><base UID='F0C7'><scale x="1.4" y="1.4"/></base></glyph>
<glyph PSName='u0CB3' UID='0CB3'><base UID='F0D7'><scale x="1.4" y="1.4"/></base><base UID='F0DA'><scale x="1.4" y="1.4"/></base></glyph>
<glyph PSName='u0CB3.base'><base UID='F0D7'><scale x="1.4" y="1.4"/></base></glyph>
<glyph PSName='u0CB3.imathra'><base UID='F0D8'><scale x="1.4" y="1.4"/></base></glyph>
<glyph PSName='u0CB3.sub'><base UID='F0D9'><scale x="1.4" y="1.4"/></base></glyph>
<glyph PSName='u0CB5' UID='0CB5'><base UID='F0C8'><scale x="1.4" y="1.4"/></base><base UID='F0DA'><scale x="1.4" y="1.4"/></base></glyph>
<glyph PSName='u0CB5.base'><base UID='F0C8'><scale x="1.4" y="1.4"/></base></glyph>
<glyph PSName='u0CB5.imathra'><base UID='F0C9'><scale x="1.4" y="1.4"/></base></glyph>
<glyph PSName='u0CB5.sub'><base UID='F0CA'><scale x="1.4" y="1.4"/></base></glyph>
<glyph PSName='u0CB6' UID='0CB6'><base UID='F0CB'><scale x="1.4" y="1.4"/></base><base UID='F0DA'><scale x="1.4" y="1.4"/></base></glyph>
<glyph PSName='u0CB6.base'><base UID='F0CB'><scale x="1.4" y="1.4"/></base></glyph>
<glyph PSName='u0CB6.imathra'><base UID='F0CC'><scale x="1.4" y="1.4"/></base></glyph>
<glyph PSName='u0CB6.sub'><base UID='F0CD'><scale x="1.4" y="1.4"/></base></glyph>
<glyph PSName='u0CB6_u0CB0_imathra'><base UID='F02A'><scale x="1.4" y="1.4"/></base></glyph>
<glyph PSName='u0CB7' UID='0CB7'><base UID='F0CE'><scale x="1.4" y="1.4"/></base><base UID='F0DA'><scale x="1.4" y="1.4"/></base></glyph>
<glyph PSName='u0CB7.base'><base UID='F0CE'><scale x="1.4" y="1.4"/></base></glyph>
<glyph PSName='u0CB7.imathra'><base UID='F0CF'><scale x="1.4" y="1.4"/></base></glyph>
<glyph PSName='u0CB7.sub'><base UID='F0D0'><scale x="1.4" y="1.4"/></base></glyph>
<glyph PSName='u0CB8' UID='0CB8'><base UID='F0D1'><scale x="1.4" y="1.4"/></base><base UID='F0DA'><scale x="1.4" y="1.4"/></base></glyph>
<glyph PSName='u0CB8.base'><base UID='F0D1'><scale x="1.4" y="1.4"/></base></glyph>
<glyph PSName='u0CB8.imathra'><base UID='F0D2'><scale x="1.4" y="1.4"/></base></glyph>
<glyph PSName='u0CB8.sub'><base UID='F0D3'><scale x="1.4" y="1.4"/></base></glyph>
<glyph PSName='u0CB9' UID='0CB9'><base UID='F0D4'><scale x="1.4" y="1.4"/></base><base UID='F0DA'><scale x="1.4" y="1.4"/></base></glyph>
<glyph PSName='u0CB9.base'><base UID='F0D4'><scale x="1.4" y="1.4"/></base></glyph>
<glyph PSName='u0CB9.imathra'><base UID='F0D5'><scale x="1.4" y="1.4"/></base></glyph>
<glyph PSName='u0CB9.sub'><base UID='F0D6'><scale x="1.4" y="1.4"/></base></glyph>
<glyph PSName='u0CBD' UID='0CBD'><base UID='F099'><scale x="1.4" y="1.4"/></base></glyph>
<glyph PSName='u0CBE' UID='0CBE'><base UID='F0DB'><scale x="1.4" y="1.4"/></base></glyph>
<glyph PSName='u0CBF' UID='0CBF'><base UID='F0DD'><scale x="1.4" y="1.4"/></base></glyph>
<glyph PSName='u0CC0' UID='0CC0'><base UID='F0DD'><scale x="1.4" y="1.4"/></base><base UID='F0DE'><scale x="1.4" y="1.4"/></base></glyph>
<glyph PSName='u0CC1' UID='0CC1'><base UID='F0DF'><scale x="1.4" y="1.4"/></base></glyph>
<glyph PSName='u0CC1.large'><base UID='F0E2'><scale x="1.4" y="1.4"/></base></glyph>
<glyph PSName='u0CC2' UID='0CC2'><base UID='F0E0'><scale x="1.4" y="1.4"/></base></glyph>
<glyph PSName='u0CC2.large'><base UID='F0E3'><scale x="1.4" y="1.4"/></base></glyph>
<glyph PSName='u0CC3' UID='0CC3'><base UID='F0E4'><scale x="1.4" y="1.4"/></base></glyph>
<glyph PSName='u0CC4' UID='0CC4'><base UID='F0E5'><scale x="1.4" y="1.4"/></base></glyph>
<glyph PSName='u0CC6' UID='0CC6'><base UID='F0E6'><scale x="1.4" y="1.4"/></base></glyph>
<glyph PSName='u0CC6.large'><base UID='F09E'><scale x="1.4" y="1.4"/></base></glyph>
<glyph PSName='u0CC7' UID='0CC7'><base UID='F0E6'><scale x="1.4" y="1.4"/></base><base UID='F0DE'><scale x="1.4" y="1.4"/></base></glyph>
<glyph PSName='u0CC8' UID='0CC8'><base UID='F0E6'><scale x="1.4" y="1.4"/></base><base UID='F0E7'><scale x="1.4" y="1.4"/></base></glyph>
<glyph PSName='u0CCA' UID='0CCA'><base UID='F0E6'><scale x="1.4" y="1.4"/></base><base UID='F0E0'><scale x="1.4" y="1.4"/></base></glyph>
<glyph PSName='u0CCA.large'><base UID='F0E6'><scale x="1.4" y="1.4"/></base><base UID='F0E3'><scale x="1.4" y="1.4"/></base></glyph>
<glyph PSName='u0CCB' UID='0CCB'><base UID='F0E6'><scale x="1.4" y="1.4"/></base><base UID='F0E0'><scale x="1.4" y="1.4"/></base><base UID='F0DE'><scale x="1.4" y="1.4"/></base></glyph>
<glyph PSName='u0CCB.large'><base UID='F0E6'><scale x="1.4" y="1.4"/></base><base UID='F0E3'><scale x="1.4" y="1.4"/></base><base UID='F0DE'><scale x="1.4" y="1.4"/></base></glyph>
<glyph PSName='u0CCC' UID='0CCC'><base UID='F0E8'><scale x="1.4" y="1.4"/></base></glyph>
<glyph PSName='u0CCD' UID='0CCD'><base UID='F0E9'><scale x="1.4" y="1.4"/></base></glyph>
<glyph PSName='u0CD5' UID='0CD5'><base UID='F0DE'><scale x="1.4" y="1.4"/></base></glyph>
<glyph PSName='u0CD6' UID='0CD6'><base UID='F0E7'><scale x="1.4" y="1.4"/></base></glyph>
<glyph PSName='u0CDE' UID='0CDE'><base UID='F08D'><scale x="1.4" y="1.4"/></base></glyph>
<glyph PSName='u0CDE.imathra'><base UID='F08E'><scale x="1.4" y="1.4"/></base></glyph>
<glyph PSName='u0CDE.sub'><base UID='F08F'><scale x="1.4" y="1.4"/></base></glyph>
<glyph PSName='u0CE0' UID='0CE0'><base UID='F046'><scale x="1.4" y="1.4"/></base><base UID='F0E0'><scale x="1.4" y="1.4"/></base></glyph>
<glyph PSName='u0CE1' UID='0CE1'><base UID='F08C'><scale x="1.4" y="1.4"/></base></glyph>
<glyph PSName='u0CE6' UID='0CE6'><base UID='F080'><scale x="1.4" y="1.4"/></base></glyph>
<glyph PSName='u0CE7' UID='0CE7'><base UID='F081'><scale x="1.4" y="1.4"/></base></glyph>
<glyph PSName='u0CE8' UID='0CE8'><base UID='F082'><scale x="1.4" y="1.4"/></base></glyph>
<glyph PSName='u0CE9' UID='0CE9'><base UID='F083'><scale x="1.4" y="1.4"/></base></glyph>
<glyph PSName='u0CEA' UID='0CEA'><base UID='F084'><scale x="1.4" y="1.4"/></base></glyph>
<glyph PSName='u0CEB' UID='0CEB'><base UID='F085'><scale x="1.4" y="1.4"/></base></glyph>
<glyph PSName='u0CEC' UID='0CEC'><base UID='F086'><scale x="1.4" y="1.4"/></base></glyph>
<glyph PSName='u0CED' UID='0CED'><base UID='F087'><scale x="1.4" y="1.4"/></base></glyph>
<glyph PSName='u0CEE' UID='0CEE'><base UID='F088'><scale x="1.4" y="1.4"/></base></glyph>
<glyph PSName='u0CEF' UID='0CEF'><base UID='F089'><scale x="1.4" y="1.4"/></base></glyph>
<glyph UID="200D"><base UID="F020"/><advance width="0"/></glyph>
<glyph UID="200C"><base UID="F020"/><advance width="0"/></glyph>
<glyph UID="200B"><base UID="F020"/><advance width="0"/></glyph>
<glyph UID="2060"><base UID="F020"/><advance width="0"/></glyph>
</glyphs>
</font>
